uas/__init__.py
uas-0.1.0.dist-info/LICENSE
uas-0.1.0.dist-info/METADATA
uas-0.1.0.dist-info/WHEEL
uas-0.1.0.dist-info/top_level.txt
uas-0.1.0.dist-info/RECORD
