Metadata-Version: 2.1
Name: uas
Version: 0.1.0
Summary: Random User-Agent
Home-page: https://github.com/sorl/uas
Author: Mikko Hellsing
Author-email: mikko@sumsum.se
License: MIT
Project-URL: Bug Tracker, https://github.com/sorl/uas/issues
Platform: UNKNOWN
Classifier: Programming Language :: Python :: 3
Classifier: License :: OSI Approved :: MIT License
Classifier: Operating System :: OS Independent
Requires-Python: >=3.6
License-File: LICENSE
